pkl_mcp/__init__.py
pkl_mcp/main.py
pkl_mcp-0.1.3.dist-info/METADATA
pkl_mcp-0.1.3.dist-info/WHEEL
pkl_mcp-0.1.3.dist-info/entry_points.txt
pkl_mcp-0.1.3.dist-info/licenses/LICENSE
pkl_mcp-0.1.3.dist-info/RECORD
