Metadata-Version: 2.4
Name: pkl-mcp
Version: 0.1.3
Summary: A Python package for MCP (Model Context Protocol) integration with Pkl configuration language
Project-URL: Homepage, https://github.com/username/pkl-mcp
Project-URL: Repository, https://github.com/username/pkl-mcp
Project-URL: Issues, https://github.com/username/pkl-mcp/issues
Project-URL: Documentation, https://github.com/username/pkl-mcp#readme
Author-email: Rob Paterson <patersoz@amazon.com>
Maintainer-email: Rob Paterson <patersoz@amazon.com>
License: MIT License
License-File: LICENSE
Keywords: configuration,mcp,model-context-protocol,pkl
Classifier: Development Status :: 3 - Alpha
Classifier: Intended Audience :: Developers
Classifier: License :: OSI Approved :: MIT License
Classifier: Operating System :: OS Independent
Classifier: Programming Language :: Python :: 3
Classifier: Programming Language :: Python :: 3.9
Classifier: Programming Language :: Python :: 3.10
Classifier: Programming Language :: Python :: 3.11
Classifier: Programming Language :: Python :: 3.12
Classifier: Topic :: Software Development :: Libraries :: Python Modules
Classifier: Topic :: Utilities
Requires-Python: >=3.9
Provides-Extra: dev
Requires-Dist: build>=1.0.0; extra == 'dev'
Requires-Dist: mypy>=1.7.0; extra == 'dev'
Requires-Dist: pre-commit>=3.5.0; extra == 'dev'
Requires-Dist: pytest-cov>=4.1.0; extra == 'dev'
Requires-Dist: pytest>=7.4.0; extra == 'dev'
Requires-Dist: ruff>=0.1.0; extra == 'dev'
Requires-Dist: twine>=4.0.0; extra == 'dev'
